xroms/__init__.py
xroms/_version.py
xroms/accessor.py
xroms/datasets.py
xroms/derived.py
xroms/interp.py
xroms/roms_seawater.py
xroms/utilities.py
xroms/vector.py
xroms/xroms.py
xroms-0.6.2.dist-info/licenses/LICENSE
xroms-0.6.2.dist-info/METADATA
xroms-0.6.2.dist-info/WHEEL
xroms-0.6.2.dist-info/top_level.txt
xroms-0.6.2.dist-info/RECORD
