Metadata-Version: 2.4
Name: xroms
Version: 0.6.2
Summary: Package for working with ROMS output in xarray
Home-page: https://github.com/xoceanmodel/xroms
Author: Rob Hetland, Kristen Thyng, Veronica Ruiz Xomchuk
License: MIT
Requires-Python: >=3.6
License-File: LICENSE
Requires-Dist: cf_xarray
Requires-Dist: dask
Requires-Dist: netcdf4
Requires-Dist: numba>=0.49
Requires-Dist: numpy
Requires-Dist: pooch
Requires-Dist: xarray
Requires-Dist: xgcm==0.8.1
Dynamic: license-file
